LICENSE
MANIFEST.in
README.md
requirements.txt
setup.py
SimpleReg.egg-info/PKG-INFO
SimpleReg.egg-info/SOURCES.txt
SimpleReg.egg-info/dependency_links.txt
SimpleReg.egg-info/entry_points.txt
SimpleReg.egg-info/not-zip-safe
SimpleReg.egg-info/requires.txt
SimpleReg.egg-info/top_level.txt
simplereg/__init__.py
simplereg/data_reader.py
simplereg/data_writer.py
simplereg/definitions.py
simplereg/flirt.py
simplereg/flirt_to_simpleitk_converter.py
simplereg/landmark_estimator.py
simplereg/landmark_visualizer.py
simplereg/nibabel_to_simpleitk_converter.py
simplereg/niftyreg.py
simplereg/niftyreg_to_simpleitk_converter.py
simplereg/point_based_registration.py
simplereg/resampler.py
simplereg/simple_itk_registration.py
simplereg/simple_itk_registration_base.py
simplereg/utilities.py
simplereg/wrap_itk_registration.py
simplereg/wrapper_registration.py
simplereg/application/__init__.py
simplereg/application/register_landmarks.py
simplereg/application/resample.py
simplereg/application/transform.py
tests/__init__.py
tests/application_test.py
tests/flirt_test.py
tests/installation_test.py
tests/landmark_registration_test.py
tests/niftyreg_test.py
tests/point_based_registration_test.py
tests/resampler_test.py
tests/run_tests.py
tests/simple_itk_registration_test.py
tests/utilities_test.py
tests/wrap_itk_registration_test.py