Metadata-Version: 2.1
Name: SimpleReg
Version: 0.3
Summary: SimpleReg is a research-focused toolkit that provides tools helpful for (medical) image registration and processing.
Home-page: https://github.com/gift-surg/SimpleReg
Author: Michael Ebner
Author-email: michael.ebner.14@ucl.ac.uk
License: BSD-3-Clause
Keywords: development registration
Platform: UNKNOWN
Classifier: Intended Audience :: Developers
Classifier: Intended Audience :: Healthcare Industry
Classifier: Intended Audience :: Science/Research
Classifier: License :: OSI Approved :: BSD License
Classifier: Topic :: Software Development :: Build Tools
Classifier: Topic :: Scientific/Engineering :: Medical Science Apps.
Classifier: Programming Language :: Python
Classifier: Programming Language :: Python :: 2
Classifier: Programming Language :: Python :: 3
